setup.py
eazy_probability/Binomialdistribution.py
eazy_probability/Gaussiandistribution.py
eazy_probability/Generaldistribution.py
eazy_probability/__init__.py
eazy_probability.egg-info/PKG-INFO
eazy_probability.egg-info/SOURCES.txt
eazy_probability.egg-info/dependency_links.txt
eazy_probability.egg-info/not-zip-safe
eazy_probability.egg-info/top_level.txt