Metadata-Version: 1.0
Name: eazy-probability
Version: 1.0
Summary: Gaussian & Binomial distributions calculator
Home-page: UNKNOWN
Author: Anuoluwapo Victor Adeyemi
Author-email: v.adeyemi.va@gmail.com
License: UNKNOWN
Platform: UNKNOWN
